CHANGES.txt
LICENSE.txt
README.txt
setup.cfg
setup.py
seal2.egg-info/PKG-INFO
seal2.egg-info/SOURCES.txt
seal2.egg-info/dependency_links.txt
seal2.egg-info/top_level.txt
seal2.egg-info/zip-safe
src/seal2.c
src/seal2.h
src/seal2module.c
src/tests.py
