Metadata-Version: 1.0
Name: seal2
Version: 1.0
Summary: SEAL2 encryption
Home-page: UNKNOWN
Author: Wichert Akkerman - Jarn
Author-email: info@jarn.com
License: GPL
Keywords: crypto,SEAL2
Platform: UNKNOWN
Classifier: Intended Audience :: Developers
Classifier: Operating System :: OS Independent
Classifier: Programming Language :: Python
Classifier: Topic :: Security :: Cryptography
Classifier: Topic :: Software Development :: Libraries :: Python Modules
